pypict.libs/libpict-54120ae9.so
pypict/capi.cpython-39-x86_64-linux-gnu.so
pypict/cmd.py
pypict/capi.pyi
pypict/api.py
pypict/_version.py
pypict/__init__.py
pypict/py.typed
pypict/__main__.py
pypict-0.3.0.dist-info/METADATA
pypict-0.3.0.dist-info/RECORD
pypict-0.3.0.dist-info/WHEEL
pypict-0.3.0.dist-info/top_level.txt
pypict-0.3.0.dist-info/LICENSE
