Metadata-Version: 2.1
Name: pypict
Version: 0.3.0
Summary: pypict: Python binding for Microsoft PICT
Home-page: https://github.com/kmaehashi/pypict
Author: Kenichi Maehashi
Author-email: webmaster@kenichimaehashi.com
License: MIT License
Platform: UNKNOWN
Requires-Python: >=3.7
License-File: LICENSE
